cypyonate/__init__.py
cypyonate/cypyonate.py
cypyonate/modules/__init__.py
cypyonate/modules/default.py
cypyonate/modules/earlybird.py
cypyonate/modules/manualmap.py
cypyonate/modules/shellcode.py
cypyonate/modules/threadhijack.py
Cypyonate-1.3.1.dist-info/LICENSE
Cypyonate-1.3.1.dist-info/METADATA
Cypyonate-1.3.1.dist-info/WHEEL
Cypyonate-1.3.1.dist-info/entry_points.txt
Cypyonate-1.3.1.dist-info/top_level.txt
Cypyonate-1.3.1.dist-info/RECORD
