Metadata-Version: 2.1
Name: Cypyonate
Version: 1.3.1
Summary: An extendable command-line injector built entirely in Python
Home-page: https://github.com/Scags/Cypyonate
Author: John Mascagni
Author-email: John Mascagni <johnmascagni@gmail.com>
License: GNU GENERAL PUBLIC LICENSE
Project-URL: homepage, https://github.com/Scags/Cypyonate
Project-URL: issues, https://github.com/Scags/Cypyonate/issues
Classifier: Programming Language :: Python :: 3
Requires-Python: >=3.10
License-File: LICENSE
